achaekek/__init__.py
achaekek/achaekek.py
achaekek/request_types.py
achaekek-0.0.12.dist-info/METADATA
achaekek-0.0.12.dist-info/WHEEL
achaekek-0.0.12.dist-info/RECORD
