Metadata-Version: 2.1
Name: achaekek
Version: 0.0.12
Summary: Python library for the Manifold markets API.
Author: TetraspaceW
Author-email: holomanga@gmail.com
Requires-Python: >=3.10,<4.0
Classifier: Programming Language :: Python :: 3
Classifier: Programming Language :: Python :: 3.10
Classifier: Programming Language :: Python :: 3.11
Classifier: Programming Language :: Python :: 3.12
Requires-Dist: requests (>=2.31.0,<3.0.0)
